odds_client/__init__.py
odds_client/default_http_client.py
odds_client/generic_sports_dataio_client.py
odds_client/manual_tests.py
odds_client/manual_tests_local.py
odds_client/sports_client_factory.py
odds_client/sports_client_nba.py
odds_client-0.23.dist-info/LICENSE
odds_client-0.23.dist-info/METADATA
odds_client-0.23.dist-info/WHEEL
odds_client-0.23.dist-info/top_level.txt
odds_client-0.23.dist-info/RECORD
