Metadata-Version: 2.1
Name: odds-client
Version: 0.23
Summary: odds api consumer for Sports Data IO
Home-page: https://github.com/ballwiz/sports-data-io-client
Author: Wedevelop's team
Author-email: sergioshev@gmail.com
License: UNKNOWN
Platform: UNKNOWN
Classifier: License :: OSI Approved :: GNU Lesser General Public License v3 (LGPLv3)
Classifier: Operating System :: POSIX :: Linux
Classifier: Programming Language :: Python :: 3
